steemdata/__init__.py
steemdata/blockchain.py
steemdata/blog.py
steemdata/helpers.py
steemdata/markets.py
steemdata/steemdata.py
steemdata/utils.py
steemdata-2.3.dist-info/DESCRIPTION.rst
steemdata-2.3.dist-info/METADATA
steemdata-2.3.dist-info/RECORD
steemdata-2.3.dist-info/WHEEL
steemdata-2.3.dist-info/dependency_links.txt
steemdata-2.3.dist-info/metadata.json
steemdata-2.3.dist-info/top_level.txt
