Metadata-Version: 2.0
Name: steemdata
Version: 2.3
Summary: Python Utilities for parsing STEEM blockchain
Home-page: https://github.com/SteemData/steemdata
Author: @furion
Author-email: _@furion.me
License: MIT
Keywords: steem
Platform: UNKNOWN
Classifier: Development Status :: 3 - Alpha
Classifier: Intended Audience :: Developers
Classifier: License :: OSI Approved :: MIT License
Classifier: Programming Language :: Python :: 3.5
Requires-Dist: funcy
Requires-Dist: pymongo
Requires-Dist: python-dateutil
Requires-Dist: requests
Requires-Dist: werkzeug
Provides-Extra: dev
Requires-Dist: check-manifest; extra == 'dev'
Provides-Extra: test
Requires-Dist: coverage; extra == 'test'
